jt64config/__init__.py
jt64config/__main__.py
jt64config-0.0.22.dist-info/LICENSE
jt64config-0.0.22.dist-info/METADATA
jt64config-0.0.22.dist-info/WHEEL
jt64config-0.0.22.dist-info/entry_points.txt
jt64config-0.0.22.dist-info/top_level.txt
jt64config-0.0.22.dist-info/RECORD
