Metadata-Version: 2.1
Name: jt64config
Version: 0.0.22
Summary: UNKNOWN
Home-page: https://github.com/KI7MT/jtsdk64-tools/tree/master/src/python/jt64config
Author: Greg Beam, KI7MT
Author-email: ki7mt@yahoo.com
License: GPLv3
Project-URL: Documentation, https://ki7mt.github.io/jtsdk64-tools
Platform: UNKNOWN
Classifier: Natural Language :: English
Classifier: Development Status :: 5 - Production/Stable
Classifier: Intended Audience :: Developers
Classifier: Topic :: Communications :: Ham Radio
Classifier: License :: OSI Approved :: GNU General Public License v3 (GPLv3)
Classifier: Operating System :: Microsoft :: Windows
Classifier: Programming Language :: Python
Classifier: Programming Language :: Python :: 3.5
Classifier: Programming Language :: Python :: 3.6
Classifier: Programming Language :: Python :: 3.7
Requires-Python: >=3.5.*
Requires-Dist: colorconsole
